[
    {
        "id": "1",
        "title": "PITBULL \u2013 PARTY AFTER PARTY",
        "location": "KRAK\u00d3W, TAURON ARENA",
        "date": "15.06.2025",
        "createdAt": "2024-01-15 10:00:00",
        "imageUrl": "https:\/\/images.pexels.com\/photos\/1190298\/pexels-photo-1190298.jpeg?auto=compress&cs=tinysrgb&w=600",
        "description": "PITBULL \u2013 PARTY AFTER PARTY to niezapomniana noc z jednym z najwi\u0119kszych gwiazd muzyki hip-hop i dance. W Tauron Arenie w Krakowie do\u015bwiadczysz energii, kt\u00f3ra przeniesie Ci\u0119 w wir tanca i zabawy. Przygotuj si\u0119 na hitowe utwory, pirotechnik\u0119 i atmosfer\u0119, kt\u00f3ra utrzyma si\u0119 do rana. To wydarzenie dla wszystkich mi\u0142o\u015bnik\u00f3w muzyki i dobrej zabawy!",
        "interestCount": 0,
        "status": ""
    },
    {
        "id": "2",
        "title": "TECHNO ROCK NIGHT",
        "location": "KATOWICE, SPODEK",
        "date": "20.07.2025",
        "createdAt": "2024-02-20 14:30:00",
        "imageUrl": "https:\/\/images.pexels.com\/photos\/1763075\/pexels-photo-1763075.jpeg?auto=compress&cs=tinysrgb&w=600",
        "description": "Techno Rock Night to fuzja nowoczesnego techno z klasycznym rockiem. W Spodku w Katowicach spotkaj si\u0119 z najlepszymi DJ-ami i zespo\u0142ami, kt\u00f3re po\u0142\u0105cz\u0105 gatunki w unikalny spos\u00f3b. Oczekuj na pot\u0119\u017cne bity, elektryzuj\u0105ce gitary i atmosfer\u0119, kt\u00f3ra przeniesie Ci\u0119 w inny wymiar muzyki.",
        "interestCount": 0,
        "status": ""
    },
    {
        "id": "3",
        "title": "ROCK LEGENDS",
        "location": "WARSZAWA",
        "date": "10.08.2026",
        "createdAt": "2024-03-10 09:15:00",
        "imageUrl": "https:\/\/images.pexels.com\/photos\/1540406\/pexels-photo-1540406.jpeg?auto=compress&cs=tinysrgb&w=600",
        "description": "ROCK LEGENDS to ho\u0142d dla najwi\u0119kszych ikon rocka. W Warszawie spotkaj si\u0119 z legendami gatunku, kt\u00f3re zagra\u0105 swoje najwi\u0119ksze hity. Przygotuj si\u0119 na pot\u0119\u017cne riffy, sol\u00f3wki i atmosfer\u0119, kt\u00f3ra przeniesie Ci\u0119 w czasy z\u0142otego wieku rocka. To wydarzenie dla prawdziwych fan\u00f3w muzyki rockowej!",
        "interestCount": 0,
        "status": ""
    },
    {
        "id": "4",
        "title": "JAZZ NIGHT",
        "location": "GDYNIA",
        "date": "05.09.2025",
        "createdAt": "2024-04-05 16:45:00",
        "imageUrl": "https:\/\/images.pexels.com\/photos\/1105666\/pexels-photo-1105666.jpeg?auto=compress&cs=tinysrgb&w=600",
        "description": "Jazz Night w Gdyni to wiecz\u00f3r po\u015bwi\u0119cony najpi\u0119kniejszym brzmieniom jazzu. Wybitni muzycy zagra\u0105 klasyczne standardy i nowoczesne interpretacje. Rozlu\u017anij si\u0119 przy fili\u017cance kawy, poczuj atmosfer\u0119 intymnych klub\u00f3w jazzowych i pozw\u00f3l, by muzyka przenios\u0142a Ci\u0119 w relaksuj\u0105cy nastr\u00f3j.",
        "interestCount": 0,
        "status": ""
    },
    {
        "id": "5",
        "title": "IMPREZA PO ODDANIU PROJEKTU",
        "location": "MIASTECZKO STUDENCKIE AGH",
        "date": "25.10.2026",
        "createdAt": "2026-02-01 21:28:00",
        "imageUrl": "https:\/\/as2.ftcdn.net\/v2\/jpg\/01\/20\/28\/25\/1000_F_120282530_gMCruc8XX2mwf5YtODLV2O1TGHzu4CAb.webp",
        "description": "Po miesi\u0105cach pracy nad projektem czas na odpoczynek! Impreza po oddaniu projektu w Miastku Studenckim AGH to okazja do celebrowania sukcesu. Baw si\u0119 z kolegami, tancz przy najlepszych hitach, jedz pyszne jedzenie i dziel si\u0119 wspomnieniami. To wydarzenie dla wszystkich, kt\u00f3rzy przyczynili si\u0119 do sukcesu projektu!",
        "interestCount": 0,
        "status": ""
    },
    {
        "id": "6",
        "title": "czad imprezka",
        "location": "m\u00f3j dom",
        "date": "04.03.2026",
        "createdAt": "2026-02-04 05:57:18",
        "imageUrl": "https:\/\/as2.ftcdn.net\/v2\/jpg\/01\/20\/28\/25\/1000_F_120282530_gMCruc8XX2mwf5YtODLV2O1TGHzu4CAb.webp",
        "description": "Czad imprezka a nie \u017cadna posiad\u00f3wka",
        "interestCount": 0,
        "status": ""
    },
    {
        "id": "7",
        "title": "im",
        "location": "asa",
        "date": "25.10.2026",
        "createdAt": "2026-02-04 05:58:47",
        "imageUrl": "https:\/\/as2.ftcdn.net\/v2\/jpg\/01\/20\/28\/25\/1000_F_120282530_gMCruc8XX2mwf5YtODLV2O1TGHzu4CAb.webp",
        "description": "aaa",
        "interestCount": 0,
        "status": ""
    },
    {
        "id": "8",
        "title": "aa",
        "location": "aa",
        "date": "04.03.2026",
        "createdAt": "2026-02-04 06:02:29",
        "imageUrl": "https:\/\/as2.ftcdn.net\/v2\/jpg\/01\/20\/28\/25\/1000_F_120282530_gMCruc8XX2mwf5YtODLV2O1TGHzu4CAb.webp",
        "description": "aa",
        "interestCount": 0,
        "status": "AKTYWNE"
    },
    {
        "id": "9",
        "title": "aaaaaaaa",
        "location": "asdasdas",
        "date": "25.10.2026",
        "createdAt": "2026-02-04 06:02:49",
        "imageUrl": "https:\/\/as2.ftcdn.net\/v2\/jpg\/01\/20\/28\/25\/1000_F_120282530_gMCruc8XX2mwf5YtODLV2O1TGHzu4CAb.webp",
        "description": "asdasdasd",
        "interestCount": 0,
        "status": "OCZEKUJACE"
    }
]